pipeline_exec/__init__.py
pipeline_exec/pipeline.py
pipeline_exec/tests.py
pipeline_exec-0.4.dist-info/LICENSE
pipeline_exec-0.4.dist-info/METADATA
pipeline_exec-0.4.dist-info/WHEEL
pipeline_exec-0.4.dist-info/top_level.txt
pipeline_exec-0.4.dist-info/RECORD
