Metadata-Version: 2.1
Name: pipeline-exec
Version: 0.4
Summary: A Pipeline to process an Object Collection
Home-page: https://github.com/Sikilabs/pipeline_exec
Author: Sikilabs Technologies Inc
Author-email: info@sikilabs.com
License: MIT
Platform: UNKNOWN
